.travis.yml
NOTICE.txt
README.rst
bootstrap.py
buildout.cfg
edrnsite.policy.sublime-project
mkrelease.cfg
setup.cfg
setup.py
travis.cfg
docs/HISTORY.txt
docs/INSTALL.txt
docs/LICENSE.txt
edrnsite/__init__.py
edrnsite.policy.egg-info/PKG-INFO
edrnsite.policy.egg-info/SOURCES.txt
edrnsite.policy.egg-info/dependency_links.txt
edrnsite.policy.egg-info/entry_points.txt
edrnsite.policy.egg-info/namespace_packages.txt
edrnsite.policy.egg-info/not-zip-safe
edrnsite.policy.egg-info/requires.txt
edrnsite.policy.egg-info/top_level.txt
edrnsite/policy/README.rst
edrnsite/policy/__init__.py
edrnsite/policy/configure.zcml
edrnsite/policy/overrides.zcml
edrnsite/policy/setuphandlers.py
edrnsite/policy/testing.py
edrnsite/policy/upgrades.py
edrnsite/policy/upgrades.zcml
edrnsite/policy/actions/__init__.py
edrnsite/policy/actions/configure.zcml
edrnsite/policy/actions/mail.py
edrnsite/policy/browser/__init__.py
edrnsite/policy/browser/configure.zcml
edrnsite/policy/browser/ingest.py
edrnsite/policy/browser/session.py
edrnsite/policy/profiles/default/cachesettings.xml
edrnsite/policy/profiles/default/contentrules.xml
edrnsite/policy/profiles/default/edrnsite.policy.flag.txt
edrnsite/policy/profiles/default/excel.gif
edrnsite/policy/profiles/default/flash.gif
edrnsite/policy/profiles/default/import_steps.xml
edrnsite/policy/profiles/default/jsregistry.xml
edrnsite/policy/profiles/default/kupu.xml
edrnsite/policy/profiles/default/mailhost.xml
edrnsite/policy/profiles/default/metadata.xml
edrnsite/policy/profiles/default/pdf.gif
edrnsite/policy/profiles/default/portlets.xml
edrnsite/policy/profiles/default/ppt.gif
edrnsite/policy/profiles/default/properties.xml
edrnsite/policy/profiles/default/propertiestool.xml
edrnsite/policy/profiles/default/qt.gif
edrnsite/policy/profiles/default/word.gif
edrnsite/policy/profiles/default/rdf/biomarkerorgans.rdf
edrnsite/policy/profiles/default/rdf/biomarkers.rdf
edrnsite/policy/profiles/default/rdf/biomuta.rdf
edrnsite/policy/profiles/default/rdf/bmdb-pubs.rdf
edrnsite/policy/profiles/default/rdf/body-systems.rdf
edrnsite/policy/profiles/default/rdf/committees.rdf
edrnsite/policy/profiles/default/rdf/datasets.rdf
edrnsite/policy/profiles/default/rdf/diseases.rdf
edrnsite/policy/profiles/default/rdf/dmcc-pubs.rdf
edrnsite/policy/profiles/default/rdf/people.rdf
